papflix_package/__init__.py
papflix_package/main.py
papflix_package/model/__init__.py
papflix_package/model/cast.py
papflix_package/model/custom_models.py
papflix_package/model/movie.py
papflix_package/qt/__init__.py
papflix_package/qt/filter.qml
papflix_package/qt/home.qml
papflix_package/qt/main.qml
papflix_package/qt/mainWindow.qml
papflix_package/qt/movie.qml
papflix_package/qt/movieDelegate.qml
papflix_package/qt/popupwindow.qml
papflix_package/qt/roundButton.qml
papflix_package/qt/swipeSource.qml
papflix_package/qt/trailerEngine.qml
papflix_package/resources/close.png
papflix_package/resources/filter.png
papflix_package/resources/maximize.png
papflix_package/resources/minimize.png
papflix_package/resources/search.png
papflix_package/resources/unknown.png
papflix_package/resources/unmaximize.png
papflix_package/resources/xclose white.png
papflix-0.0.11.dist-info/LICENSE
papflix-0.0.11.dist-info/METADATA
papflix-0.0.11.dist-info/WHEEL
papflix-0.0.11.dist-info/top_level.txt
papflix-0.0.11.dist-info/RECORD
