Metadata-Version: 2.1
Name: papflix
Version: 0.0.11
Summary: A small example package
Home-page: https://github.com/pypa/sampleproject
Author: kpaparid
Author-email: kpaparid@gmail.com
License: UNKNOWN
Project-URL: Bug Tracker, https://github.com/pypa/sampleproject/issues
Platform: UNKNOWN
Classifier: Programming Language :: Python :: 3
Classifier: License :: OSI Approved :: MIT License
Classifier: Operating System :: OS Independent
Requires-Python: >=3.6
License-File: LICENSE
Requires-Dist: pyjarowinkler (==1.8)
Requires-Dist: PySide2 (==5.15.2.1)
Requires-Dist: rapidfuzz (==2.0.11)
Requires-Dist: requests (==2.27.1)
Requires-Dist: setuptools (==58.1.0)
Requires-Dist: tmdbv3api (==1.7.6)
